tune_easy/__init__.py
tune_easy/_group_time_split.py
tune_easy/_util_methods.py
tune_easy/all_in_one_tuning.py
tune_easy/elasticnet_tuning.py
tune_easy/lgbm_tuning.py
tune_easy/linearregression_tuning.py
tune_easy/logisticregression_tuning.py
tune_easy/param_tuning.py
tune_easy/rf_tuning.py
tune_easy/svm_tuning.py
tune_easy/xgb_tuning.py
tune_easy-0.2.1.dist-info/LICENSE
tune_easy-0.2.1.dist-info/METADATA
tune_easy-0.2.1.dist-info/WHEEL
tune_easy-0.2.1.dist-info/top_level.txt
tune_easy-0.2.1.dist-info/RECORD
