Metadata-Version: 2.1
Name: tune-easy
Version: 0.2.1
Summary: tune-easy: A hyperparameter tuning tool, extremely easy to use.
Home-page: https://github.com/c60evaporator/tune-easy
Author: Kenta Nakamura
Author-email: c60evaporator@gmail.com
Maintainer: Kenta Nakamura
Maintainer-email: c60evaporator@gmail.com
License: BSD 3-Clause
Download-URL: https://github.com/c60evaporator/tune-easy
Platform: UNKNOWN
Classifier: Intended Audience :: Science/Research
Classifier: License :: OSI Approved :: BSD License
Classifier: Programming Language :: Python :: 3
Classifier: Programming Language :: Python :: 3.6
Classifier: Programming Language :: Python :: 3.7
Classifier: Programming Language :: Python :: 3.8
Classifier: Programming Language :: Python :: 3.9
Classifier: Programming Language :: Python :: 3 :: Only
Classifier: Topic :: Scientific/Engineering
Classifier: Topic :: Scientific/Engineering :: Visualization
Classifier: Topic :: Scientific/Engineering :: Artificial Intelligence
Classifier: Topic :: Multimedia :: Graphics
Classifier: Framework :: Matplotlib
Requires-Python: >=3.6
Requires-Dist: scikit-learn (>=0.24.2)
Requires-Dist: matplotlib (>=3.3.4)
Requires-Dist: seaborn (>=0.11.0)
Requires-Dist: numpy (>=1.20.3)
Requires-Dist: pandas (>=1.2.4)
Requires-Dist: optuna (>=2.7.0)
Requires-Dist: bayesian-optimization (>=1.2.0)
Requires-Dist: mlflow (>=1.17.0)
Requires-Dist: lightgbm (>=3.3.2)
Requires-Dist: xgboost (>=1.4.2)
Requires-Dist: seaborn-analyzer (>=0.2.11)
